panns_AT_inference/__init__.py
panns_AT_inference/config.py
panns_AT_inference/inference.py
panns_AT_inference/models.py
panns_AT_inference/pytorch_utils.py
panns_AT_inference-0.1.4.dist-info/LICENSE.MIT
panns_AT_inference-0.1.4.dist-info/METADATA
panns_AT_inference-0.1.4.dist-info/WHEEL
panns_AT_inference-0.1.4.dist-info/top_level.txt
panns_AT_inference-0.1.4.dist-info/RECORD
