Metadata-Version: 2.1
Name: panns-AT-inference
Version: 0.1.4
Summary: panns_AT_inference: audio tagging inference toolbox
Home-page: https://github.com/StefanoGiacomelli/panns_AT_inference
Author: Qiuqiang Kong, Stefano Giacomelli (Ph.D. student UnivAQ)
Author-email: qiuqiangkong@gmail.com, stefano.giacomelli@graduate.univaq.it
Classifier: Programming Language :: Python :: 3
Classifier: License :: OSI Approved :: MIT License
Classifier: Operating System :: OS Independent
Requires-Python: >=3.6
License-File: LICENSE.MIT
Requires-Dist: numpy
Requires-Dist: torch
Requires-Dist: matplotlib
Requires-Dist: librosa
Requires-Dist: torchlibrosa
